{
  "title": "Loop",
  "id": "loop",
  "system": "fate-core-official",
  "joinTheme": "default",
  "coreVersion": "11.315",
  "compatibility": {
    "minimum": "11",
    "verified": "11"
  },
  "systemVersion": "4.6.8",
  "lastPlayed": "Wed Mar 27 2024 10:13:53 GMT+0000 (Horário Padrão da Europa Ocidental)",
  "background": "worlds/loop/images/20240126-cover-loop.png",
  "playtime": 152905,
  "description": "<p>Três épocas, três pessoas e um destino.</p>",
  "manifest": "https://github.com/gandb/taulukko-content-campaigns-loop/main/world.json",
  "download": "https://github.com/gandb/taulukko-content-campaigns-loop/zip/master",
  "url": "https://github.com/gandb/taulukko-content-campaigns-loop",
  "version": "1.0.0",
  "packs": [
    {
      "label": "Mass Edit: Presets (MAIN)",
      "type": "JournalEntry",
      "ownership": {
        "GAMEMASTER": "NONE",
        "PLAYER": "NONE",
        "ASSISTANT": "NONE"
      },
      "name": "mass-edit-presets-main",
      "path": "packs/mass-edit-presets-main",
      "system": "fate-core-official",
      "flags": {}
    }
  ]
}